qanswer_sdk/__init__.py
qanswer_sdk/api/__init__.py
qanswer_sdk/api/admin_api.py
qanswer_sdk/api/ai_assistant_access_rights_api.py
qanswer_sdk/api/ai_assistant_api.py
qanswer_sdk/api/bot_slack_api.py
qanswer_sdk/api/branding_api.py
qanswer_sdk/api/chatbot_api.py
qanswer_sdk/api/connector_audio_api.py
qanswer_sdk/api/connector_document_api.py
qanswer_sdk/api/connector_e_consilium_api.py
qanswer_sdk/api/connector_e_consilium_search_index_api_api.py
qanswer_sdk/api/connector_google_drive_api.py
qanswer_sdk/api/connector_imapapi_api.py
qanswer_sdk/api/connector_one_drive_api.py
qanswer_sdk/api/connector_onenote_api.py
qanswer_sdk/api/connector_pinecone_api.py
qanswer_sdk/api/connector_publication_office_api_api.py
qanswer_sdk/api/connector_qn_a_api.py
qanswer_sdk/api/connector_rdf_answer_api.py
qanswer_sdk/api/connector_rdf_api.py
qanswer_sdk/api/connector_sharepoint_api.py
qanswer_sdk/api/connector_websearch_api.py
qanswer_sdk/api/connector_website_api.py
qanswer_sdk/api/connectors_api.py
qanswer_sdk/api/connectors_data_api.py
qanswer_sdk/api/conversation_logs_api.py
qanswer_sdk/api/converters_api.py
qanswer_sdk/api/dataset_config_api.py
qanswer_sdk/api/debug_api.py
qanswer_sdk/api/health_check_api_api.py
qanswer_sdk/api/llm_api.py
qanswer_sdk/api/mcp_api.py
qanswer_sdk/api/payment_api.py
qanswer_sdk/api/socket_api.py
qanswer_sdk/api/speech_to_text_api.py
qanswer_sdk/api/task_ai_excel_api.py
qanswer_sdk/api/task_chat_api.py
qanswer_sdk/api/task_rdf_linker_api.py
qanswer_sdk/api/task_rdf_sparql_endpoint_api.py
qanswer_sdk/api/task_rdf_text_linker_api.py
qanswer_sdk/api/task_relation_extraction_api.py
qanswer_sdk/api/task_report_copilot_api.py
qanswer_sdk/api/task_search_api.py
qanswer_sdk/api/task_text2sparql_api.py
qanswer_sdk/api/task_text_classification_api.py
qanswer_sdk/api/tool_embedder_api.py
qanswer_sdk/api/tool_llm_api.py
qanswer_sdk/api/unit_organizations_api.py
qanswer_sdk/api/unit_teams_api.py
qanswer_sdk/api/unit_user_api.py
qanswer_sdk-3.1505.0.dist-info/METADATA
qanswer_sdk-3.1505.0.dist-info/WHEEL
qanswer_sdk-3.1505.0.dist-info/RECORD
